dai_post_processor/__init__.py
dai_post_processor/post_processor.py
dai_post_processor/run_GUI.py
post_processor_pi-0.0.9.data/scripts/run_GUI.py
post_processor_pi-0.0.9.dist-info/LICENSE.txt
post_processor_pi-0.0.9.dist-info/METADATA
post_processor_pi-0.0.9.dist-info/WHEEL
post_processor_pi-0.0.9.dist-info/top_level.txt
post_processor_pi-0.0.9.dist-info/RECORD
