Metadata-Version: 2.1
Name: post-processor-pi
Version: 0.0.9
Summary: Post processor for Document AI
Home-page: https://github.com/paoloitaliani/post-processor-pi
Author: Paolo Italiani
Author-email: paoita@hotmail.it
License: MIT
Platform: UNKNOWN
Requires-Dist: numpy
Requires-Dist: matplotlib
